rcsb_embedding_model/__init__.py
rcsb_embedding_model/rcsb_structure_embedding.py
rcsb_embedding_model/cli/args_utils.py
rcsb_embedding_model/cli/inference.py
rcsb_embedding_model/dataset/esm_prot_from_chain.py
rcsb_embedding_model/dataset/esm_prot_from_structure.py
rcsb_embedding_model/dataset/resdiue_assembly_embedding_from_structure.py
rcsb_embedding_model/dataset/residue_assembly_embedding_from_tensor_file.py
rcsb_embedding_model/dataset/residue_embedding_from_structure.py
rcsb_embedding_model/dataset/residue_embedding_from_tensor_file.py
rcsb_embedding_model/dataset/untils/__init__.py
rcsb_embedding_model/dataset/untils/utils.py
rcsb_embedding_model/inference/assembly_inferece.py
rcsb_embedding_model/inference/chain_inference.py
rcsb_embedding_model/inference/esm_inference.py
rcsb_embedding_model/inference/structure_inference.py
rcsb_embedding_model/model/layers.py
rcsb_embedding_model/model/residue_embedding_aggregator.py
rcsb_embedding_model/modules/chain_module.py
rcsb_embedding_model/modules/esm_module.py
rcsb_embedding_model/modules/structure_module.py
rcsb_embedding_model/types/api_types.py
rcsb_embedding_model/utils/data.py
rcsb_embedding_model/utils/model.py
rcsb_embedding_model/utils/structure_parser.py
rcsb_embedding_model/utils/structure_provider.py
rcsb_embedding_model/utils/esm/loaders.py
rcsb_embedding_model/writer/batch_writer.py
rcsb_embedding_model-0.0.48.dist-info/METADATA
rcsb_embedding_model-0.0.48.dist-info/WHEEL
rcsb_embedding_model-0.0.48.dist-info/entry_points.txt
rcsb_embedding_model-0.0.48.dist-info/licenses/LICENSE.md
rcsb_embedding_model-0.0.48.dist-info/RECORD
