Metadata-Version: 2.4
Name: rcsb-embedding-model
Version: 0.0.48
Summary: Protein Embedding Model for Structure Search
Project-URL: Homepage, https://github.com/rcsb/rcsb-embedding-model
Project-URL: Issues, https://github.com/rcsb/rcsb-embedding-model/issues
Author-email: Joan Segura <joan.segura@rcsb.org>
License: # Cambrian Non-Commercial License Agreement
License-File: LICENSE.md
Classifier: Operating System :: OS Independent
Classifier: Programming Language :: Python :: 3
Requires-Python: >=3.11
Requires-Dist: biotite>=1.5.0
Requires-Dist: esm>=3.2.0
Requires-Dist: hf-xet>=1.1.10
Requires-Dist: httpx>=0.28.1
Requires-Dist: huggingface-hub>=0.30.2
Requires-Dist: importlib-metadata>=8.7.0
Requires-Dist: lightning>=2.5.0
Requires-Dist: typer>=0.15.0
